translator/__init__.py
translator/admin.py
translator/apps.py
translator/forms.py
translator/models.py
translator/tests.py
translator/views.py
translator/widgets.py
translator/migrations/__init__.py
translator/static/translator/css/translator.css
translator/static/translator/js/init_translator.js
translator/static/translator/js/translator/translator.min.js
translator/templates/translator/translator.html
dj_translator-0.0.1.dist-info/LICENSE
dj_translator-0.0.1.dist-info/METADATA
dj_translator-0.0.1.dist-info/WHEEL
dj_translator-0.0.1.dist-info/top_level.txt
dj_translator-0.0.1.dist-info/RECORD
