Metadata-Version: 2.1
Name: dj-translator
Version: 0.0.1
Summary: A Django module for text translation using local editor.
Home-page: https://github.com/amiroooamiran/django-translator
Author: Amirhossein Amiran
Author-email: amiran.amirhossein@gmail.com
License: MIT License
Classifier: Environment :: Web Environment
Classifier: Framework :: Django
Classifier: Framework :: Django :: 5.0
Classifier: Intended Audience :: Developers
Classifier: License :: OSI Approved :: MIT License
Classifier: Operating System :: OS Independent
Classifier: Programming Language :: Python
Classifier: Programming Language :: Python :: 3.12
Classifier: Topic :: Internet :: WWW/HTTP
Classifier: Topic :: Internet :: WWW/HTTP :: Dynamic Content
License-File: LICENSE
Requires-Dist: Django >=5.0
Requires-Dist: django-tinymce
